[
    {
        "Tasks": [
            {
                "id": 1692301570777,
                "title": "lllllll",
                "timeStamp": 1692301620000,
                "group": "General",
                "checked": false,
                "type": "normal"
            },
            {
                "id": 1692302649588,
                "title": "asdasd",
                "timeStamp": 1692302649588,
                "group": "General",
                "checked": null,
                "type": "quick"
            }
        ]
    },
    {
        "Groups": [
            {
                "id": 888,
                "title": "General",
                "color": "#6074F9"
            },
            {
                "id": 1692302842650,
                "title": "asdasd",
                "color": "#e42b6a"
            },
            {
                "id": 1692306896794,
                "title": "asdad",
                "color": "#5abb56"
            }
        ]
    }
]